setup.cfg
setup.py
conviz/__init__.py
conviz/gradient_ascent_optimizer.py
conviz/visualizer.py
conviz.egg-info/PKG-INFO
conviz.egg-info/SOURCES.txt
conviz.egg-info/dependency_links.txt
conviz.egg-info/top_level.txt
conviz/models/__init__.py
conviz/models/cifar10.py
conviz/tests/__init__.py
conviz/tests/test_gradient_ascent_optimizer.py
conviz/tests/test_image_util.py
conviz/tests/test_models.py
conviz/tests/test_visualizer.py
conviz/utils/__init__.py
conviz/utils/data_util.py
conviz/utils/image_util.py