Metadata-Version: 1.1
Name: conviz
Version: 0.3
Summary: A convolutional neural layer visualization library
Home-page: https://github.com/PhTrempe/conviz
Author: Philippe Trempe
Author-email: ph.trempe@gmail.com
License: MIT
Download-URL: https://github.com/phtrempe/conviz/archive/0.3.tar.gz
Keywords: convolutional,neural,network,layer,visualization
Platform: UNKNOWN
Requires: numpy
Requires: scipy
Requires: pillow
Requires: keras
